lib_dzne_analyze_seq_further/__init__.py
lib_dzne_analyze_seq_further/regions.py
lib_dzne_analyze_seq_further-0.2.5.dist-info/LICENSE.txt
lib_dzne_analyze_seq_further-0.2.5.dist-info/METADATA
lib_dzne_analyze_seq_further-0.2.5.dist-info/WHEEL
lib_dzne_analyze_seq_further-0.2.5.dist-info/top_level.txt
lib_dzne_analyze_seq_further-0.2.5.dist-info/RECORD
