Metadata-Version: 2.1
Name: lib_dzne_analyze_seq_further
Version: 0.2.5
Summary: This package was created to contain all parts of the aBASE-like sequence read analysis that are self-contained and needed to be easily accessed. 
Author-email: Johannes <johannes-programming@posteo.org>
License: Copyright © 2022 Johannes
Project-URL: Download, https://pypi.org/project/lib-dzne-analyze-seq-further/#files
Project-URL: Source, https://github.com/johannes-programming/lib_dzne_analyze_seq_further
Keywords: BASE,brain,antibody
Classifier: License :: OSI Approved :: MIT License
Classifier: Programming Language :: Python
Classifier: Programming Language :: Python :: 3
Requires-Python: >=3.11
License-File: LICENSE.txt
Requires-Dist: lib-dzne-math >=0.2.3
Requires-Dist: lib-dzne-seq >=0.2.2
Requires-Dist: lib-dzne-filedata >=0.5
